gcn_graphdb_retriever/__init__.py
gcn_graphdb_retriever/chains.py
gcn_graphdb_retriever/chains_old.py
gcn_graphdb_retriever/gcn_graph_builder.py
gcn_graphdb_retriever/main.py
gcn_graphdb_retriever/prompts.py
gcn_graphdb_retriever/py.typed
gcn_graphdb_retriever/subject_KEE_pipeline.py
gcn_graphdb_retriever/utils.py
gcn_graphdb_retriever-0.1.0.dist-info/METADATA
gcn_graphdb_retriever-0.1.0.dist-info/WHEEL
gcn_graphdb_retriever-0.1.0.dist-info/entry_points.txt
gcn_graphdb_retriever-0.1.0.dist-info/licenses/LICENSE
gcn_graphdb_retriever-0.1.0.dist-info/RECORD
