Metadata-Version: 2.4
Name: gcn-graphdb-retriever
Version: 0.1.0
Summary: Add your description here
Author-email: yuliu <yuliu@gzu.edu.cn>
License-File: LICENSE
Requires-Python: >=3.10
Requires-Dist: aiofiles>=24.1.0
Requires-Dist: chromadb>=0.6.3
Requires-Dist: huggingface-hub>=0.30.2
Requires-Dist: jinja2>=3.1.6
Requires-Dist: langchain-chroma>=0.2.3
Requires-Dist: langchain-community>=0.3.22
Requires-Dist: langchain-neo4j>=0.4.0
Requires-Dist: langchain-ollama>=0.3.2
Requires-Dist: langchain>=0.3.24
Requires-Dist: neo4j>=5.28.1
Requires-Dist: pandas>=2.2.3
